web_share_ftp/__init__.py
web_share_ftp/__main__.py
web_share_ftp/cli.py
web_share_ftp/share.py
web_share_ftp-1.0.dist-info/LICENSE
web_share_ftp-1.0.dist-info/METADATA
web_share_ftp-1.0.dist-info/WHEEL
web_share_ftp-1.0.dist-info/entry_points.txt
web_share_ftp-1.0.dist-info/top_level.txt
web_share_ftp-1.0.dist-info/RECORD
