Metadata-Version: 2.1
Name: web-share-ftp
Version: 1.0
Summary: A Flask App to Share Files Within the Same Network
Home-page: https://github.com/ovebepari/webshare
Author: Ove Bepari
Author-email: ovebepari@gmail.com
License: UNKNOWN
Platform: UNKNOWN
Classifier: Programming Language :: Python :: 3
Classifier: Environment :: Web Environment
Classifier: Intended Audience :: Developers
Classifier: Topic :: Internet :: WWW/HTTP :: WSGI :: Application
Requires-Python: >=3
Requires-Dist: flask
Requires-Dist: click
